baseballfaker/__init__.py
baseballfaker/baseball.py
SportFaker-0.0.1.dist-info/LICENSE
SportFaker-0.0.1.dist-info/METADATA
SportFaker-0.0.1.dist-info/WHEEL
SportFaker-0.0.1.dist-info/top_level.txt
SportFaker-0.0.1.dist-info/RECORD
