Metadata-Version: 2.1
Name: SportFaker
Version: 0.0.1
Summary: A small example package
Author-email: Josh Kolodny <kolo.josh@gmail.com>
Project-URL: Homepage, https://github.com/pypa/sportfaker
Project-URL: Bug Tracker, https://github.com/pypa/sportfaker/issues
Classifier: Programming Language :: Python :: 3
Classifier: License :: OSI Approved :: MIT License
Classifier: Operating System :: OS Independent
Requires-Python: >=3.7
License-File: LICENSE
